[{"registry":"ripencc","type":"ipv4","start":"109.95.152.0","prefix":21,"cidr":"109.95.152.0/21","cc":"PL","date":"20100104"},{"registry":"ripencc","type":"ipv4","start":"195.88.50.0","prefix":23,"cidr":"195.88.50.0/23","cc":"PL","date":"20090212"},{"registry":"ripencc","type":"ipv4","start":"195.191.232.0","prefix":23,"cidr":"195.191.232.0/23","cc":"PL","date":"20100311"},{"registry":"ripencc","type":"ipv6","start":"2001:67c:1c8::","prefix":48,"cidr":"2001:67c:1c8::/48","cc":"PL","date":"20100408"}]
