[{"registry":"ripencc","type":"ipv4","start":"91.223.151.0","prefix":24,"cidr":"91.223.151.0/24","cc":"DE","date":"20110221"},{"registry":"ripencc","type":"ipv4","start":"185.89.56.0","prefix":22,"cidr":"185.89.56.0/22","cc":"DE","date":"20150223"},{"registry":"ripencc","type":"ipv4","start":"194.117.254.0","prefix":23,"cidr":"194.117.254.0/23","cc":"DE","date":"20050919"},{"registry":"ripencc","type":"ipv6","start":"2a05:d580::","prefix":29,"cidr":"2a05:d580::/29","cc":"DE","date":"20150220"}]
