[{"registry":"ripencc","type":"ipv4","start":"185.194.172.0","prefix":22,"cidr":"185.194.172.0/22","cc":"TR","date":"20170315"},{"registry":"ripencc","type":"ipv4","start":"194.156.236.0","prefix":22,"cidr":"194.156.236.0/22","cc":"TR","date":"20180530"},{"registry":"ripencc","type":"ipv6","start":"2a07:f280::","prefix":29,"cidr":"2a07:f280::/29","cc":"TR","date":"20180601"},{"registry":"ripencc","type":"ipv6","start":"2a0a:86c0::","prefix":29,"cidr":"2a0a:86c0::/29","cc":"TR","date":"20170407"}]
