[{"registry":"ripencc","type":"ipv4","start":"167.150.90.0","prefix":23,"cidr":"167.150.90.0/23","cc":"BE","date":"19930802"},{"registry":"ripencc","type":"ipv6","start":"2001:678:110::","prefix":48,"cidr":"2001:678:110::/48","cc":"BE","date":"20240315"},{"registry":"ripencc","type":"ipv6","start":"2001:678:c44::","prefix":48,"cidr":"2001:678:c44::/48","cc":"BE","date":"20200205"},{"registry":"ripencc","type":"ipv6","start":"2001:678:c6c::","prefix":48,"cidr":"2001:678:c6c::/48","cc":"BE","date":"20200224"},{"registry":"ripencc","type":"ipv6","start":"2001:67c:e70::","prefix":48,"cidr":"2001:67c:e70::/48","cc":"BE","date":"20240417"},{"registry":"ripencc","type":"ipv6","start":"2001:67c:e74::","prefix":48,"cidr":"2001:67c:e74::/48","cc":"BE","date":"20240417"},{"registry":"ripencc","type":"ipv6","start":"2001:67c:e78::","prefix":48,"cidr":"2001:67c:e78::/48","cc":"BE","date":"20240417"},{"registry":"ripencc","type":"ipv6","start":"2001:67c:e7c::","prefix":48,"cidr":"2001:67c:e7c::/48","cc":"BE","date":"20240417"},{"registry":"ripencc","type":"ipv6","start":"2001:67c:2908::","prefix":48,"cidr":"2001:67c:2908::/48","cc":"BE","date":"20201221"},{"registry":"ripencc","type":"ipv6","start":"2001:67c:2ea8::","prefix":48,"cidr":"2001:67c:2ea8::/48","cc":"BE","date":"20200224"}]
