[{"registry":"ripencc","type":"ipv4","start":"193.176.32.0","prefix":24,"cidr":"193.176.32.0/24","cc":"CZ","date":"20250806"},{"registry":"ripencc","type":"ipv4","start":"194.164.239.0","prefix":24,"cidr":"194.164.239.0/24","cc":"CZ","date":"19960307"},{"registry":"ripencc","type":"ipv4","start":"195.200.23.0","prefix":24,"cidr":"195.200.23.0/24","cc":"CZ","date":"19960509"},{"registry":"ripencc","type":"ipv6","start":"2a14:2040::","prefix":29,"cidr":"2a14:2040::/29","cc":"CZ","date":"20240315"}]
