[{"registry":"afrinic","type":"ipv4","start":"41.188.128.0","prefix":18,"cidr":"41.188.128.0/18","cc":"TZ","date":"20090108"},{"registry":"afrinic","type":"ipv4","start":"41.221.32.0","prefix":20,"cidr":"41.221.32.0/20","cc":"TZ","date":"20070521"},{"registry":"afrinic","type":"ipv4","start":"155.12.0.0","prefix":17,"cidr":"155.12.0.0/17","cc":"TZ","date":"20150429"},{"registry":"afrinic","type":"ipv4","start":"196.45.32.0","prefix":20,"cidr":"196.45.32.0/20","cc":"TZ","date":"20040429"},{"registry":"afrinic","type":"ipv6","start":"2001:4258::","prefix":32,"cidr":"2001:4258::/32","cc":"TZ","date":"20060531"}]
