[{"registry":"ripencc","type":"ipv4","start":"5.179.120.0","prefix":21,"cidr":"5.179.120.0/21","cc":"FR","date":"20120808"},{"registry":"ripencc","type":"ipv4","start":"31.216.16.0","prefix":20,"cidr":"31.216.16.0/20","cc":"FR","date":"20110509"},{"registry":"ripencc","type":"ipv4","start":"46.21.112.0","prefix":20,"cidr":"46.21.112.0/20","cc":"FR","date":"20101104"},{"registry":"ripencc","type":"ipv4","start":"185.7.160.0","prefix":22,"cidr":"185.7.160.0/22","cc":"FR","date":"20121023"},{"registry":"ripencc","type":"ipv6","start":"2a02:27d0::","prefix":32,"cidr":"2a02:27d0::/32","cc":"FR","date":"20101028"}]
