[{"registry":"ripencc","type":"ipv4","start":"93.157.12.0","prefix":22,"cidr":"93.157.12.0/22","cc":"UA","date":"20080519"},{"registry":"ripencc","type":"ipv4","start":"185.1.16.0","prefix":24,"cidr":"185.1.16.0/24","cc":"UA","date":"20130717"},{"registry":"ripencc","type":"ipv4","start":"193.254.232.0","prefix":23,"cidr":"193.254.232.0/23","cc":"UA","date":"20020923"},{"registry":"ripencc","type":"ipv6","start":"2001:7f8:7b::","prefix":48,"cidr":"2001:7f8:7b::/48","cc":"UA","date":"20130717"}]
