[{"registry":"ripencc","type":"ipv4","start":"185.107.128.0","prefix":22,"cidr":"185.107.128.0/22","cc":"RU","date":"20150703"},{"registry":"ripencc","type":"ipv4","start":"185.171.100.0","prefix":22,"cidr":"185.171.100.0/22","cc":"RU","date":"20161005"},{"registry":"ripencc","type":"ipv4","start":"195.170.208.0","prefix":22,"cidr":"195.170.208.0/22","cc":"RU","date":"19970506"},{"registry":"ripencc","type":"ipv4","start":"195.170.212.0","prefix":22,"cidr":"195.170.212.0/22","cc":"RU","date":"19970506"},{"registry":"ripencc","type":"ipv6","start":"2a0a:cd00::","prefix":32,"cidr":"2a0a:cd00::/32","cc":"RU","date":"20161005"}]
