[{"registry":"ripencc","type":"ipv4","start":"194.153.151.0","prefix":24,"cidr":"194.153.151.0/24","cc":"DE","date":"20000407"},{"registry":"ripencc","type":"ipv4","start":"195.158.32.0","prefix":19,"cidr":"195.158.32.0/19","cc":"DE","date":"19971230"},{"registry":"ripencc","type":"ipv4","start":"195.250.48.0","prefix":24,"cidr":"195.250.48.0/24","cc":"DE","date":"20060123"},{"registry":"ripencc","type":"ipv4","start":"212.218.0.0","prefix":16,"cidr":"212.218.0.0/16","cc":"DE","date":"19980409"},{"registry":"ripencc","type":"ipv6","start":"2001:4cd8::","prefix":29,"cidr":"2001:4cd8::/29","cc":"DE","date":"20050628"}]
